{
    "a": 0,
    "jobs": [
        {
            "big": 1,
            "due_date": 260,
            "pos_time": 5,
            "status": 3,
            "blocked": 1,
            "operations": [
                {
                    "type": 0,
                    "processing_time": 13
                }
            ]
        },
        {
            "big": 1,
            "due_date": 163,
            "pos_time": 5,
            "status": 3,
            "blocked": 0,
            "operations": [
                {
                    "type": 0,
                    "processing_time": 28
                }
            ]
        },
        {
            "big": 0,
            "due_date": 406,
            "pos_time": 5,
            "status": 2,
            "blocked": 0,
            "operations": [
                {
                    "type": 0,
                    "processing_time": 36
                }
            ]
        },
        {
            "big": 1,
            "due_date": 132,
            "pos_time": 5,
            "status": 2,
            "blocked": 1,
            "operations": [
                {
                    "type": 0,
                    "processing_time": 45
                }
            ]
        },
        {
            "big": 0,
            "due_date": 212,
            "pos_time": 5,
            "status": 0,
            "blocked": 2,
            "operations": [
                {
                    "type": 1,
                    "processing_time": 12
                }
            ]
        },
        {
            "big": 0,
            "due_date": 253,
            "pos_time": 5,
            "status": 3,
            "blocked": 0,
            "operations": [
                {
                    "type": 1,
                    "processing_time": 55
                }
            ]
        },
        {
            "big": 1,
            "due_date": 219,
            "pos_time": 5,
            "status": 3,
            "blocked": 1,
            "operations": [
                {
                    "type": 1,
                    "processing_time": 36
                }
            ]
        },
        {
            "big": 1,
            "due_date": 293,
            "pos_time": 5,
            "status": 0,
            "blocked": 1,
            "operations": [
                {
                    "type": 0,
                    "processing_time": 43
                }
            ]
        },
        {
            "big": 1,
            "due_date": 433,
            "pos_time": 5,
            "status": 0,
            "blocked": 1,
            "operations": [
                {
                    "type": 1,
                    "processing_time": 34
                }
            ]
        },
        {
            "big": 0,
            "due_date": 189,
            "pos_time": 5,
            "status": 2,
            "blocked": 1,
            "operations": [
                {
                    "type": 1,
                    "processing_time": 33
                }
            ]
        },
        {
            "big": 1,
            "due_date": 161,
            "pos_time": 5,
            "status": 1,
            "blocked": 1,
            "operations": [
                {
                    "type": 1,
                    "processing_time": 18
                }
            ]
        },
        {
            "big": 0,
            "due_date": 274,
            "pos_time": 5,
            "status": 1,
            "blocked": 0,
            "operations": [
                {
                    "type": 1,
                    "processing_time": 22
                }
            ]
        },
        {
            "big": 1,
            "due_date": 326,
            "pos_time": 5,
            "status": 3,
            "blocked": 0,
            "operations": [
                {
                    "type": 0,
                    "processing_time": 21
                }
            ]
        },
        {
            "big": 1,
            "due_date": 253,
            "pos_time": 5,
            "status": 1,
            "blocked": 0,
            "operations": [
                {
                    "type": 0,
                    "processing_time": 22
                }
            ]
        },
        {
            "big": 1,
            "due_date": 318,
            "pos_time": 5,
            "status": 3,
            "blocked": 0,
            "operations": [
                {
                    "type": 0,
                    "processing_time": 16
                }
            ]
        },
        {
            "big": 0,
            "due_date": 228,
            "pos_time": 5,
            "status": 3,
            "blocked": 2,
            "operations": [
                {
                    "type": 0,
                    "processing_time": 37
                }
            ]
        },
        {
            "big": 0,
            "due_date": 384,
            "pos_time": 5,
            "status": 3,
            "blocked": 1,
            "operations": [
                {
                    "type": 1,
                    "processing_time": 15
                }
            ]
        },
        {
            "big": 1,
            "due_date": 344,
            "pos_time": 5,
            "status": 0,
            "blocked": 0,
            "operations": [
                {
                    "type": 1,
                    "processing_time": 31
                }
            ]
        },
        {
            "big": 0,
            "due_date": 346,
            "pos_time": 5,
            "status": 0,
            "blocked": 2,
            "operations": [
                {
                    "type": 1,
                    "processing_time": 12
                }
            ]
        },
        {
            "big": 1,
            "due_date": 176,
            "pos_time": 5,
            "status": 0,
            "blocked": 0,
            "operations": [
                {
                    "type": 1,
                    "processing_time": 12
                }
            ]
        },
        {
            "big": 0,
            "due_date": 159,
            "pos_time": 5,
            "status": 1,
            "blocked": 1,
            "operations": [
                {
                    "type": 0,
                    "processing_time": 20
                }
            ]
        },
        {
            "big": 1,
            "due_date": 271,
            "pos_time": 5,
            "status": 2,
            "blocked": 1,
            "operations": [
                {
                    "type": 0,
                    "processing_time": 57
                }
            ]
        },
        {
            "big": 1,
            "due_date": 257,
            "pos_time": 5,
            "status": 0,
            "blocked": 1,
            "operations": [
                {
                    "type": 1,
                    "processing_time": 35
                }
            ]
        },
        {
            "big": 0,
            "due_date": 395,
            "pos_time": 5,
            "status": 0,
            "blocked": 2,
            "operations": [
                {
                    "type": 0,
                    "processing_time": 48
                }
            ]
        },
        {
            "big": 0,
            "due_date": 210,
            "pos_time": 5,
            "status": 1,
            "blocked": 0,
            "operations": [
                {
                    "type": 0,
                    "processing_time": 26
                }
            ]
        },
        {
            "big": 1,
            "due_date": 322,
            "pos_time": 5,
            "status": 1,
            "blocked": 2,
            "operations": [
                {
                    "type": 0,
                    "processing_time": 44
                }
            ]
        },
        {
            "big": 0,
            "due_date": 266,
            "pos_time": 5,
            "status": 1,
            "blocked": 0,
            "operations": [
                {
                    "type": 1,
                    "processing_time": 55
                }
            ]
        },
        {
            "big": 1,
            "due_date": 192,
            "pos_time": 5,
            "status": 2,
            "blocked": 1,
            "operations": [
                {
                    "type": 1,
                    "processing_time": 54
                }
            ]
        },
        {
            "big": 1,
            "due_date": 389,
            "pos_time": 5,
            "status": 0,
            "blocked": 2,
            "operations": [
                {
                    "type": 0,
                    "processing_time": 41
                }
            ]
        },
        {
            "big": 1,
            "due_date": 373,
            "pos_time": 5,
            "status": 2,
            "blocked": 0,
            "operations": [
                {
                    "type": 0,
                    "processing_time": 26
                }
            ]
        },
        {
            "big": 1,
            "due_date": 163,
            "pos_time": 5,
            "status": 3,
            "blocked": 0,
            "operations": [
                {
                    "type": 0,
                    "processing_time": 17
                }
            ]
        },
        {
            "big": 0,
            "due_date": 313,
            "pos_time": 5,
            "status": 0,
            "blocked": 0,
            "operations": [
                {
                    "type": 0,
                    "processing_time": 46
                }
            ]
        },
        {
            "big": 0,
            "due_date": 344,
            "pos_time": 5,
            "status": 3,
            "blocked": 0,
            "operations": [
                {
                    "type": 0,
                    "processing_time": 20
                }
            ]
        },
        {
            "big": 0,
            "due_date": 234,
            "pos_time": 5,
            "status": 1,
            "blocked": 2,
            "operations": [
                {
                    "type": 0,
                    "processing_time": 41
                }
            ]
        },
        {
            "big": 1,
            "due_date": 281,
            "pos_time": 5,
            "status": 3,
            "blocked": 0,
            "operations": [
                {
                    "type": 1,
                    "processing_time": 23
                }
            ]
        }
    ]
}