{
    "a": 40,
    "jobs": [
        {
            "big": 1,
            "due_date": 142,
            "pos_time": 5,
            "status": 0,
            "blocked": 0,
            "operations": [
                {
                    "type": 0,
                    "processing_time": 42
                }
            ]
        },
        {
            "big": 0,
            "due_date": 422,
            "pos_time": 5,
            "status": 1,
            "blocked": 1,
            "operations": [
                {
                    "type": 1,
                    "processing_time": 33
                },
                {
                    "type": 0,
                    "processing_time": 29
                }
            ]
        },
        {
            "big": 0,
            "due_date": 328,
            "pos_time": 5,
            "status": 3,
            "blocked": 2,
            "operations": [
                {
                    "type": 0,
                    "processing_time": 19
                },
                {
                    "type": 1,
                    "processing_time": 25
                }
            ]
        },
        {
            "big": 0,
            "due_date": 181,
            "pos_time": 5,
            "status": 3,
            "blocked": 1,
            "operations": [
                {
                    "type": 0,
                    "processing_time": 23
                }
            ]
        },
        {
            "big": 0,
            "due_date": 183,
            "pos_time": 5,
            "status": 3,
            "blocked": 2,
            "operations": [
                {
                    "type": 1,
                    "processing_time": 57
                }
            ]
        },
        {
            "big": 0,
            "due_date": 233,
            "pos_time": 5,
            "status": 2,
            "blocked": 1,
            "operations": [
                {
                    "type": 1,
                    "processing_time": 42
                }
            ]
        },
        {
            "big": 0,
            "due_date": 351,
            "pos_time": 5,
            "status": 3,
            "blocked": 0,
            "operations": [
                {
                    "type": 1,
                    "processing_time": 27
                },
                {
                    "type": 0,
                    "processing_time": 54
                }
            ]
        },
        {
            "big": 1,
            "due_date": 223,
            "pos_time": 5,
            "status": 3,
            "blocked": 2,
            "operations": [
                {
                    "type": 0,
                    "processing_time": 46
                }
            ]
        },
        {
            "big": 1,
            "due_date": 273,
            "pos_time": 5,
            "status": 3,
            "blocked": 1,
            "operations": [
                {
                    "type": 0,
                    "processing_time": 42
                }
            ]
        },
        {
            "big": 1,
            "due_date": 368,
            "pos_time": 5,
            "status": 2,
            "blocked": 0,
            "operations": [
                {
                    "type": 0,
                    "processing_time": 33
                },
                {
                    "type": 1,
                    "processing_time": 59
                }
            ]
        },
        {
            "big": 1,
            "due_date": 235,
            "pos_time": 5,
            "status": 0,
            "blocked": 1,
            "operations": [
                {
                    "type": 0,
                    "processing_time": 13
                }
            ]
        },
        {
            "big": 1,
            "due_date": 284,
            "pos_time": 5,
            "status": 2,
            "blocked": 2,
            "operations": [
                {
                    "type": 0,
                    "processing_time": 15
                },
                {
                    "type": 1,
                    "processing_time": 17
                }
            ]
        },
        {
            "big": 0,
            "due_date": 197,
            "pos_time": 5,
            "status": 2,
            "blocked": 2,
            "operations": [
                {
                    "type": 0,
                    "processing_time": 38
                },
                {
                    "type": 1,
                    "processing_time": 45
                }
            ]
        },
        {
            "big": 0,
            "due_date": 157,
            "pos_time": 5,
            "status": 1,
            "blocked": 0,
            "operations": [
                {
                    "type": 1,
                    "processing_time": 53
                }
            ]
        },
        {
            "big": 0,
            "due_date": 333,
            "pos_time": 5,
            "status": 3,
            "blocked": 2,
            "operations": [
                {
                    "type": 1,
                    "processing_time": 33
                }
            ]
        },
        {
            "big": 1,
            "due_date": 206,
            "pos_time": 5,
            "status": 3,
            "blocked": 2,
            "operations": [
                {
                    "type": 1,
                    "processing_time": 26
                }
            ]
        },
        {
            "big": 0,
            "due_date": 205,
            "pos_time": 5,
            "status": 1,
            "blocked": 2,
            "operations": [
                {
                    "type": 0,
                    "processing_time": 23
                },
                {
                    "type": 1,
                    "processing_time": 26
                }
            ]
        },
        {
            "big": 1,
            "due_date": 132,
            "pos_time": 5,
            "status": 3,
            "blocked": 2,
            "operations": [
                {
                    "type": 0,
                    "processing_time": 52
                }
            ]
        },
        {
            "big": 1,
            "due_date": 408,
            "pos_time": 5,
            "status": 1,
            "blocked": 2,
            "operations": [
                {
                    "type": 0,
                    "processing_time": 21
                },
                {
                    "type": 1,
                    "processing_time": 52
                }
            ]
        },
        {
            "big": 0,
            "due_date": 163,
            "pos_time": 5,
            "status": 1,
            "blocked": 1,
            "operations": [
                {
                    "type": 1,
                    "processing_time": 48
                }
            ]
        },
        {
            "big": 1,
            "due_date": 274,
            "pos_time": 5,
            "status": 0,
            "blocked": 1,
            "operations": [
                {
                    "type": 1,
                    "processing_time": 34
                },
                {
                    "type": 0,
                    "processing_time": 58
                }
            ]
        },
        {
            "big": 1,
            "due_date": 264,
            "pos_time": 5,
            "status": 2,
            "blocked": 1,
            "operations": [
                {
                    "type": 1,
                    "processing_time": 31
                }
            ]
        },
        {
            "big": 0,
            "due_date": 234,
            "pos_time": 5,
            "status": 1,
            "blocked": 2,
            "operations": [
                {
                    "type": 1,
                    "processing_time": 40
                }
            ]
        },
        {
            "big": 0,
            "due_date": 327,
            "pos_time": 5,
            "status": 0,
            "blocked": 0,
            "operations": [
                {
                    "type": 0,
                    "processing_time": 41
                }
            ]
        },
        {
            "big": 0,
            "due_date": 188,
            "pos_time": 5,
            "status": 1,
            "blocked": 2,
            "operations": [
                {
                    "type": 1,
                    "processing_time": 23
                },
                {
                    "type": 0,
                    "processing_time": 33
                }
            ]
        },
        {
            "big": 1,
            "due_date": 232,
            "pos_time": 5,
            "status": 1,
            "blocked": 1,
            "operations": [
                {
                    "type": 1,
                    "processing_time": 23
                },
                {
                    "type": 0,
                    "processing_time": 29
                }
            ]
        },
        {
            "big": 0,
            "due_date": 310,
            "pos_time": 5,
            "status": 2,
            "blocked": 1,
            "operations": [
                {
                    "type": 0,
                    "processing_time": 46
                },
                {
                    "type": 1,
                    "processing_time": 39
                }
            ]
        },
        {
            "big": 0,
            "due_date": 330,
            "pos_time": 5,
            "status": 0,
            "blocked": 1,
            "operations": [
                {
                    "type": 1,
                    "processing_time": 47
                },
                {
                    "type": 0,
                    "processing_time": 16
                }
            ]
        },
        {
            "big": 0,
            "due_date": 417,
            "pos_time": 5,
            "status": 1,
            "blocked": 1,
            "operations": [
                {
                    "type": 1,
                    "processing_time": 23
                },
                {
                    "type": 0,
                    "processing_time": 52
                }
            ]
        },
        {
            "big": 0,
            "due_date": 225,
            "pos_time": 5,
            "status": 1,
            "blocked": 1,
            "operations": [
                {
                    "type": 1,
                    "processing_time": 53
                },
                {
                    "type": 0,
                    "processing_time": 56
                }
            ]
        },
        {
            "big": 0,
            "due_date": 398,
            "pos_time": 5,
            "status": 2,
            "blocked": 0,
            "operations": [
                {
                    "type": 0,
                    "processing_time": 10
                },
                {
                    "type": 1,
                    "processing_time": 11
                }
            ]
        },
        {
            "big": 1,
            "due_date": 343,
            "pos_time": 5,
            "status": 1,
            "blocked": 2,
            "operations": [
                {
                    "type": 1,
                    "processing_time": 34
                },
                {
                    "type": 0,
                    "processing_time": 10
                }
            ]
        },
        {
            "big": 1,
            "due_date": 359,
            "pos_time": 5,
            "status": 3,
            "blocked": 0,
            "operations": [
                {
                    "type": 0,
                    "processing_time": 33
                }
            ]
        }
    ]
}