{
    "a": 80,
    "jobs": [
        {
            "big": 0,
            "due_date": 269,
            "pos_time": 5,
            "status": 0,
            "blocked": 1,
            "operations": [
                {
                    "type": 1,
                    "processing_time": 53
                }
            ]
        },
        {
            "big": 1,
            "due_date": 307,
            "pos_time": 5,
            "status": 0,
            "blocked": 2,
            "operations": [
                {
                    "type": 1,
                    "processing_time": 15
                }
            ]
        },
        {
            "big": 0,
            "due_date": 406,
            "pos_time": 5,
            "status": 0,
            "blocked": 2,
            "operations": [
                {
                    "type": 1,
                    "processing_time": 47
                }
            ]
        },
        {
            "big": 0,
            "due_date": 409,
            "pos_time": 5,
            "status": 2,
            "blocked": 1,
            "operations": [
                {
                    "type": 0,
                    "processing_time": 51
                }
            ]
        },
        {
            "big": 0,
            "due_date": 201,
            "pos_time": 5,
            "status": 0,
            "blocked": 0,
            "operations": [
                {
                    "type": 0,
                    "processing_time": 19
                }
            ]
        },
        {
            "big": 0,
            "due_date": 193,
            "pos_time": 5,
            "status": 1,
            "blocked": 2,
            "operations": [
                {
                    "type": 1,
                    "processing_time": 22
                }
            ]
        },
        {
            "big": 1,
            "due_date": 185,
            "pos_time": 5,
            "status": 1,
            "blocked": 2,
            "operations": [
                {
                    "type": 0,
                    "processing_time": 16
                }
            ]
        },
        {
            "big": 0,
            "due_date": 278,
            "pos_time": 5,
            "status": 0,
            "blocked": 0,
            "operations": [
                {
                    "type": 1,
                    "processing_time": 21
                }
            ]
        },
        {
            "big": 1,
            "due_date": 284,
            "pos_time": 5,
            "status": 1,
            "blocked": 2,
            "operations": [
                {
                    "type": 0,
                    "processing_time": 51
                }
            ]
        },
        {
            "big": 0,
            "due_date": 496,
            "pos_time": 5,
            "status": 2,
            "blocked": 1,
            "operations": [
                {
                    "type": 0,
                    "processing_time": 60
                }
            ]
        },
        {
            "big": 0,
            "due_date": 199,
            "pos_time": 5,
            "status": 3,
            "blocked": 0,
            "operations": [
                {
                    "type": 0,
                    "processing_time": 59
                }
            ]
        },
        {
            "big": 0,
            "due_date": 285,
            "pos_time": 5,
            "status": 2,
            "blocked": 0,
            "operations": [
                {
                    "type": 1,
                    "processing_time": 38
                }
            ]
        },
        {
            "big": 0,
            "due_date": 382,
            "pos_time": 5,
            "status": 0,
            "blocked": 2,
            "operations": [
                {
                    "type": 1,
                    "processing_time": 34
                }
            ]
        },
        {
            "big": 0,
            "due_date": 258,
            "pos_time": 5,
            "status": 1,
            "blocked": 0,
            "operations": [
                {
                    "type": 1,
                    "processing_time": 30
                }
            ]
        },
        {
            "big": 0,
            "due_date": 528,
            "pos_time": 5,
            "status": 0,
            "blocked": 0,
            "operations": [
                {
                    "type": 0,
                    "processing_time": 15
                }
            ]
        },
        {
            "big": 1,
            "due_date": 359,
            "pos_time": 5,
            "status": 3,
            "blocked": 2,
            "operations": [
                {
                    "type": 0,
                    "processing_time": 44
                }
            ]
        },
        {
            "big": 0,
            "due_date": 506,
            "pos_time": 5,
            "status": 3,
            "blocked": 1,
            "operations": [
                {
                    "type": 0,
                    "processing_time": 59
                }
            ]
        },
        {
            "big": 1,
            "due_date": 406,
            "pos_time": 5,
            "status": 2,
            "blocked": 1,
            "operations": [
                {
                    "type": 0,
                    "processing_time": 50
                }
            ]
        },
        {
            "big": 0,
            "due_date": 364,
            "pos_time": 5,
            "status": 2,
            "blocked": 1,
            "operations": [
                {
                    "type": 0,
                    "processing_time": 56
                }
            ]
        },
        {
            "big": 1,
            "due_date": 568,
            "pos_time": 5,
            "status": 2,
            "blocked": 1,
            "operations": [
                {
                    "type": 0,
                    "processing_time": 54
                }
            ]
        },
        {
            "big": 0,
            "due_date": 400,
            "pos_time": 5,
            "status": 2,
            "blocked": 2,
            "operations": [
                {
                    "type": 0,
                    "processing_time": 41
                }
            ]
        },
        {
            "big": 0,
            "due_date": 433,
            "pos_time": 5,
            "status": 1,
            "blocked": 1,
            "operations": [
                {
                    "type": 1,
                    "processing_time": 26
                }
            ]
        },
        {
            "big": 1,
            "due_date": 475,
            "pos_time": 5,
            "status": 0,
            "blocked": 1,
            "operations": [
                {
                    "type": 1,
                    "processing_time": 31
                }
            ]
        },
        {
            "big": 1,
            "due_date": 567,
            "pos_time": 5,
            "status": 3,
            "blocked": 1,
            "operations": [
                {
                    "type": 0,
                    "processing_time": 30
                }
            ]
        },
        {
            "big": 0,
            "due_date": 194,
            "pos_time": 5,
            "status": 1,
            "blocked": 2,
            "operations": [
                {
                    "type": 0,
                    "processing_time": 59
                }
            ]
        },
        {
            "big": 1,
            "due_date": 218,
            "pos_time": 5,
            "status": 0,
            "blocked": 0,
            "operations": [
                {
                    "type": 0,
                    "processing_time": 12
                }
            ]
        },
        {
            "big": 1,
            "due_date": 442,
            "pos_time": 5,
            "status": 1,
            "blocked": 1,
            "operations": [
                {
                    "type": 1,
                    "processing_time": 39
                }
            ]
        },
        {
            "big": 0,
            "due_date": 391,
            "pos_time": 5,
            "status": 1,
            "blocked": 1,
            "operations": [
                {
                    "type": 1,
                    "processing_time": 50
                }
            ]
        },
        {
            "big": 0,
            "due_date": 487,
            "pos_time": 5,
            "status": 1,
            "blocked": 0,
            "operations": [
                {
                    "type": 0,
                    "processing_time": 13
                }
            ]
        },
        {
            "big": 0,
            "due_date": 494,
            "pos_time": 5,
            "status": 1,
            "blocked": 0,
            "operations": [
                {
                    "type": 0,
                    "processing_time": 16
                }
            ]
        },
        {
            "big": 1,
            "due_date": 305,
            "pos_time": 5,
            "status": 0,
            "blocked": 1,
            "operations": [
                {
                    "type": 0,
                    "processing_time": 39
                }
            ]
        },
        {
            "big": 1,
            "due_date": 301,
            "pos_time": 5,
            "status": 3,
            "blocked": 1,
            "operations": [
                {
                    "type": 0,
                    "processing_time": 57
                }
            ]
        },
        {
            "big": 0,
            "due_date": 416,
            "pos_time": 5,
            "status": 0,
            "blocked": 0,
            "operations": [
                {
                    "type": 1,
                    "processing_time": 44
                }
            ]
        },
        {
            "big": 1,
            "due_date": 552,
            "pos_time": 5,
            "status": 1,
            "blocked": 0,
            "operations": [
                {
                    "type": 0,
                    "processing_time": 38
                }
            ]
        },
        {
            "big": 1,
            "due_date": 431,
            "pos_time": 5,
            "status": 2,
            "blocked": 1,
            "operations": [
                {
                    "type": 1,
                    "processing_time": 45
                }
            ]
        },
        {
            "big": 0,
            "due_date": 252,
            "pos_time": 5,
            "status": 0,
            "blocked": 1,
            "operations": [
                {
                    "type": 1,
                    "processing_time": 53
                }
            ]
        },
        {
            "big": 1,
            "due_date": 228,
            "pos_time": 5,
            "status": 3,
            "blocked": 1,
            "operations": [
                {
                    "type": 1,
                    "processing_time": 30
                }
            ]
        },
        {
            "big": 0,
            "due_date": 269,
            "pos_time": 5,
            "status": 0,
            "blocked": 0,
            "operations": [
                {
                    "type": 0,
                    "processing_time": 47
                }
            ]
        },
        {
            "big": 1,
            "due_date": 347,
            "pos_time": 5,
            "status": 2,
            "blocked": 2,
            "operations": [
                {
                    "type": 1,
                    "processing_time": 46
                }
            ]
        },
        {
            "big": 1,
            "due_date": 324,
            "pos_time": 5,
            "status": 1,
            "blocked": 0,
            "operations": [
                {
                    "type": 1,
                    "processing_time": 60
                }
            ]
        },
        {
            "big": 0,
            "due_date": 481,
            "pos_time": 5,
            "status": 2,
            "blocked": 1,
            "operations": [
                {
                    "type": 1,
                    "processing_time": 47
                }
            ]
        },
        {
            "big": 1,
            "due_date": 416,
            "pos_time": 5,
            "status": 0,
            "blocked": 0,
            "operations": [
                {
                    "type": 1,
                    "processing_time": 55
                }
            ]
        },
        {
            "big": 1,
            "due_date": 400,
            "pos_time": 5,
            "status": 3,
            "blocked": 2,
            "operations": [
                {
                    "type": 0,
                    "processing_time": 53
                }
            ]
        },
        {
            "big": 1,
            "due_date": 175,
            "pos_time": 5,
            "status": 3,
            "blocked": 0,
            "operations": [
                {
                    "type": 1,
                    "processing_time": 19
                }
            ]
        },
        {
            "big": 1,
            "due_date": 474,
            "pos_time": 5,
            "status": 1,
            "blocked": 1,
            "operations": [
                {
                    "type": 0,
                    "processing_time": 34
                }
            ]
        },
        {
            "big": 0,
            "due_date": 413,
            "pos_time": 5,
            "status": 3,
            "blocked": 0,
            "operations": [
                {
                    "type": 0,
                    "processing_time": 36
                }
            ]
        },
        {
            "big": 0,
            "due_date": 400,
            "pos_time": 5,
            "status": 1,
            "blocked": 1,
            "operations": [
                {
                    "type": 1,
                    "processing_time": 20
                }
            ]
        },
        {
            "big": 1,
            "due_date": 487,
            "pos_time": 5,
            "status": 1,
            "blocked": 2,
            "operations": [
                {
                    "type": 0,
                    "processing_time": 32
                }
            ]
        },
        {
            "big": 1,
            "due_date": 349,
            "pos_time": 5,
            "status": 1,
            "blocked": 0,
            "operations": [
                {
                    "type": 1,
                    "processing_time": 59
                }
            ]
        }
    ]
}