[

    {
        "big" : 0,
        "due_date" : 8,
        "pos_time" : 1,
        "operations" : [
            {
                "type" : 2,
                "pocessing_time" : 6
            }
        ]
    },



    {
        "big" : 1,
        "due_date" : 11,
        "pos_time" : 1,
        "operations" : [
            {
                "type" : 1,
                "pocessing_time" : 5
            },
            {
                "type" : 2,
                "pocessing_time" : 2
            }
        ]
    },



    {
        "big" : 1,
        "due_date" : 13,
        "pos_time" : 1,
        "operations" : [
            {
                "type" : 1,
                "pocessing_time" : 2
            }
        ]
    }
    
]
