{
    "a": 30,
    "jobs": [
        {
            "big": 0,
            "due_date": 119,
            "pos_time": 5,
            "status": 0,
            "blocked": 0,
            "operations": [
                {
                    "type": 1,
                    "processing_time": 34
                }
            ]
        },
        {
            "big": 0,
            "due_date": 107,
            "pos_time": 5,
            "status": 0,
            "blocked": 0,
            "operations": [
                {
                    "type": 1,
                    "processing_time": 47
                }
            ]
        },
        {
            "big": 0,
            "due_date": 122,
            "pos_time": 5,
            "status": 0,
            "blocked": 0,
            "operations": [
                {
                    "type": 1,
                    "processing_time": 24
                },
                {
                    "type": 0,
                    "processing_time": 14
                }
            ]
        },
        {
            "big": 0,
            "due_date": 75,
            "pos_time": 5,
            "status": 0,
            "blocked": 0,
            "operations": [
                {
                    "type": 1,
                    "processing_time": 46
                }
            ]
        },
        {
            "big": 0,
            "due_date": 194,
            "pos_time": 5,
            "status": 0,
            "blocked": 0,
            "operations": [
                {
                    "type": 1,
                    "processing_time": 23
                },
                {
                    "type": 0,
                    "processing_time": 33
                }
            ]
        },
        {
            "big": 1,
            "due_date": 189,
            "pos_time": 5,
            "status": 0,
            "blocked": 0,
            "operations": [
                {
                    "type": 1,
                    "processing_time": 38
                },
                {
                    "type": 0,
                    "processing_time": 46
                }
            ]
        },
        {
            "big": 1,
            "due_date": 114,
            "pos_time": 5,
            "status": 0,
            "blocked": 0,
            "operations": [
                {
                    "type": 1,
                    "processing_time": 17
                }
            ]
        }
    ]
}