{
    "a": 100,
    "jobs": [
        {
            "big": 0,
            "due_date": 53,
            "pos_time": 5,
            "status": 3,
            "blocked": 1,
            "operations": [
                {
                    "type": 1,
                    "processing_time": 55
                }
            ]
        },
        {
            "big": 1,
            "due_date": 58,
            "pos_time": 5,
            "status": 3,
            "blocked": 0,
            "operations": [
                {
                    "type": 0,
                    "processing_time": 35
                }
            ]
        },
        {
            "big": 1,
            "due_date": 192,
            "pos_time": 5,
            "status": 1,
            "blocked": 1,
            "operations": [
                {
                    "type": 1,
                    "processing_time": 22
                },
                {
                    "type": 0,
                    "processing_time": 50
                }
            ]
        },
        {
            "big": 1,
            "due_date": 80,
            "pos_time": 5,
            "status": 2,
            "blocked": 1,
            "operations": [
                {
                    "type": 1,
                    "processing_time": 56
                },
                {
                    "type": 0,
                    "processing_time": 42
                }
            ]
        },
        {
            "big": 1,
            "due_date": 153,
            "pos_time": 5,
            "status": 0,
            "blocked": 2,
            "operations": [
                {
                    "type": 1,
                    "processing_time": 49
                }
            ]
        },
        {
            "big": 0,
            "due_date": 152,
            "pos_time": 5,
            "status": 1,
            "blocked": 0,
            "operations": [
                {
                    "type": 1,
                    "processing_time": 39
                },
                {
                    "type": 0,
                    "processing_time": 51
                }
            ]
        },
        {
            "big": 0,
            "due_date": 69,
            "pos_time": 5,
            "status": 2,
            "blocked": 1,
            "operations": [
                {
                    "type": 0,
                    "processing_time": 31
                }
            ]
        },
        {
            "big": 0,
            "due_date": 92,
            "pos_time": 5,
            "status": 1,
            "blocked": 0,
            "operations": [
                {
                    "type": 1,
                    "processing_time": 55
                }
            ]
        },
        {
            "big": 1,
            "due_date": 142,
            "pos_time": 5,
            "status": 1,
            "blocked": 2,
            "operations": [
                {
                    "type": 1,
                    "processing_time": 33
                },
                {
                    "type": 0,
                    "processing_time": 28
                }
            ]
        },
        {
            "big": 1,
            "due_date": 67,
            "pos_time": 5,
            "status": 0,
            "blocked": 1,
            "operations": [
                {
                    "type": 0,
                    "processing_time": 56
                }
            ]
        }
    ]
}