[
    {
        "big": 1,
        "due_date": 170,
        "pos_time": 5,
        "status": 1,
        "blocked": 0,
        "operations": [
            {
                "type": 1,
                "processing_time": 28
            },
            {
                "type": 2,
                "processing_time": 30
            }
        ]
    },
    {
        "big": 1,
        "due_date": 125,
        "pos_time": 5,
        "status": 3,
        "blocked": 0,
        "operations": [
            {
                "type": 1,
                "processing_time": 33
            },
            {
                "type": 2,
                "processing_time": 11
            }
        ]
    },
    {
        "big": 1,
        "due_date": 247,
        "pos_time": 5,
        "status": 3,
        "blocked": 0,
        "operations": [
            {
                "type": 2,
                "processing_time": 13
            }
        ]
    },
    {
        "big": 0,
        "due_date": 172,
        "pos_time": 5,
        "status": 0,
        "blocked": 1,
        "operations": [
            {
                "type": 1,
                "processing_time": 28
            }
        ]
    },
    {
        "big": 0,
        "due_date": 171,
        "pos_time": 5,
        "status": 0,
        "blocked": 1,
        "operations": [
            {
                "type": 1,
                "processing_time": 48
            }
        ]
    },
    {
        "big": 0,
        "due_date": 108,
        "pos_time": 5,
        "status": 0,
        "blocked": 1,
        "operations": [
            {
                "type": 1,
                "processing_time": 26
            },
            {
                "type": 2,
                "processing_time": 26
            }
        ]
    },
    {
        "big": 1,
        "due_date": 94,
        "pos_time": 5,
        "status": 0,
        "blocked": 1,
        "operations": [
            {
                "type": 1,
                "processing_time": 50
            }
        ]
    },
    {
        "big": 0,
        "due_date": 247,
        "pos_time": 5,
        "status": 2,
        "blocked": 1,
        "operations": [
            {
                "type": 2,
                "processing_time": 60
            },
            {
                "type": 1,
                "processing_time": 39
            }
        ]
    }
]