{
    "a": 30,
    "jobs": [
        {
            "big": 1,
            "due_date": 100,
            "pos_time": 5,
            "status": 0,
            "blocked": 0,
            "operations": [
                {
                    "type": 0,
                    "processing_time": 48
                }
            ]
        },
        {
            "big": 1,
            "due_date": 84,
            "pos_time": 5,
            "status": 0,
            "blocked": 0,
            "operations": [
                {
                    "type": 1,
                    "processing_time": 14
                },
                {
                    "type": 0,
                    "processing_time": 35
                }
            ]
        },
        {
            "big": 1,
            "due_date": 61,
            "pos_time": 5,
            "status": 0,
            "blocked": 0,
            "operations": [
                {
                    "type": 1,
                    "processing_time": 14
                }
            ]
        },
        {
            "big": 1,
            "due_date": 96,
            "pos_time": 5,
            "status": 0,
            "blocked": 0,
            "operations": [
                {
                    "type": 1,
                    "processing_time": 49
                }
            ]
        },
        {
            "big": 1,
            "due_date": 131,
            "pos_time": 5,
            "status": 0,
            "blocked": 0,
            "operations": [
                {
                    "type": 1,
                    "processing_time": 49
                },
                {
                    "type": 0,
                    "processing_time": 24
                }
            ]
        }
    ]
}