{
    "a": 70,
    "jobs": [
        {
            "big": 1,
            "due_date": 72,
            "pos_time": 5,
            "status": 0,
            "blocked": 0,
            "operations": [
                {
                    "type": 0,
                    "processing_time": 17
                }
            ]
        },
        {
            "big": 0,
            "due_date": 82,
            "pos_time": 5,
            "status": 0,
            "blocked": 0,
            "operations": [
                {
                    "type": 1,
                    "processing_time": 32
                }
            ]
        },
        {
            "big": 1,
            "due_date": 126,
            "pos_time": 5,
            "status": 0,
            "blocked": 0,
            "operations": [
                {
                    "type": 0,
                    "processing_time": 16
                },
                {
                    "type": 1,
                    "processing_time": 23
                }
            ]
        },
        {
            "big": 1,
            "due_date": 131,
            "pos_time": 5,
            "status": 0,
            "blocked": 0,
            "operations": [
                {
                    "type": 1,
                    "processing_time": 53
                },
                {
                    "type": 0,
                    "processing_time": 55
                }
            ]
        }
    ]
}