{
    "a": 60,
    "jobs": [
        {
            "big": 1,
            "due_date": 65,
            "pos_time": 5,
            "status": 0,
            "blocked": 0,
            "operations": [
                {
                    "type": 0,
                    "processing_time": 29
                }
            ]
        },
        {
            "big": 1,
            "due_date": 158,
            "pos_time": 5,
            "status": 0,
            "blocked": 0,
            "operations": [
                {
                    "type": 1,
                    "processing_time": 47
                },
                {
                    "type": 0,
                    "processing_time": 42
                }
            ]
        },
        {
            "big": 1,
            "due_date": 96,
            "pos_time": 5,
            "status": 0,
            "blocked": 0,
            "operations": [
                {
                    "type": 1,
                    "processing_time": 28
                },
                {
                    "type": 0,
                    "processing_time": 24
                }
            ]
        }
    ]
}