[
    {
        "big": 0,
        "due_date": 144,
        "pos_time": 5,
        "status": 2,
        "blocked": 0,
        "operations": [
            {
                "type": 2,
                "processing_time": 31
            },
            {
                "type": 1,
                "processing_time": 53
            }
        ]
    },
    {
        "big": 1,
        "due_date": 149,
        "pos_time": 5,
        "status": 2,
        "blocked": 2,
        "operations": [
            {
                "type": 1,
                "processing_time": 47
            }
        ]
    },
    {
        "big": 0,
        "due_date": 198,
        "pos_time": 5,
        "status": 3,
        "blocked": 1,
        "operations": [
            {
                "type": 1,
                "processing_time": 24
            },
            {
                "type": 2,
                "processing_time": 36
            }
        ]
    },
    {
        "big": 0,
        "due_date": 211,
        "pos_time": 5,
        "status": 3,
        "blocked": 2,
        "operations": [
            {
                "type": 1,
                "processing_time": 24
            }
        ]
    },
    {
        "big": 0,
        "due_date": 61,
        "pos_time": 5,
        "status": 1,
        "blocked": 1,
        "operations": [
            {
                "type": 1,
                "processing_time": 16
            },
            {
                "type": 2,
                "processing_time": 29
            }
        ]
    }
]