{
    "a": 0,
    "jobs": [
        {
            "big": 0,
            "due_date": 117,
            "pos_time": 5,
            "status": 2,
            "blocked": 0,
            "operations": [
                {
                    "type": 1,
                    "processing_time": 39
                }
            ]
        },
        {
            "big": 1,
            "due_date": 86,
            "pos_time": 5,
            "status": 1,
            "blocked": 0,
            "operations": [
                {
                    "type": 2,
                    "processing_time": 49
                },
                {
                    "type": 1,
                    "processing_time": 15
                }
            ]
        },
        {
            "big": 1,
            "due_date": 245,
            "pos_time": 5,
            "status": 1,
            "blocked": 1,
            "operations": [
                {
                    "type": 1,
                    "processing_time": 13
                },
                {
                    "type": 2,
                    "processing_time": 32
                }
            ]
        },
        {
            "big": 0,
            "due_date": 67,
            "pos_time": 5,
            "status": 0,
            "blocked": 1,
            "operations": [
                {
                    "type": 1,
                    "processing_time": 49
                },
                {
                    "type": 2,
                    "processing_time": 24
                }
            ]
        },
        {
            "big": 0,
            "due_date": 140,
            "pos_time": 5,
            "status": 3,
            "blocked": 1,
            "operations": [
                {
                    "type": 1,
                    "processing_time": 41
                }
            ]
        },
        {
            "big": 0,
            "due_date": 179,
            "pos_time": 5,
            "status": 3,
            "blocked": 0,
            "operations": [
                {
                    "type": 1,
                    "processing_time": 45
                },
                {
                    "type": 2,
                    "processing_time": 57
                }
            ]
        },
        {
            "big": 1,
            "due_date": 119,
            "pos_time": 5,
            "status": 0,
            "blocked": 2,
            "operations": [
                {
                    "type": 2,
                    "processing_time": 15
                }
            ]
        },
        {
            "big": 1,
            "due_date": 217,
            "pos_time": 5,
            "status": 0,
            "blocked": 1,
            "operations": [
                {
                    "type": 1,
                    "processing_time": 57
                }
            ]
        },
        {
            "big": 0,
            "due_date": 250,
            "pos_time": 5,
            "status": 1,
            "blocked": 1,
            "operations": [
                {
                    "type": 1,
                    "processing_time": 46
                },
                {
                    "type": 2,
                    "processing_time": 11
                }
            ]
        },
        {
            "big": 1,
            "due_date": 166,
            "pos_time": 5,
            "status": 0,
            "blocked": 1,
            "operations": [
                {
                    "type": 2,
                    "processing_time": 39
                }
            ]
        },
        {
            "big": 0,
            "due_date": 66,
            "pos_time": 5,
            "status": 0,
            "blocked": 1,
            "operations": [
                {
                    "type": 1,
                    "processing_time": 27
                }
            ]
        },
        {
            "big": 0,
            "due_date": 127,
            "pos_time": 5,
            "status": 0,
            "blocked": 1,
            "operations": [
                {
                    "type": 2,
                    "processing_time": 55
                }
            ]
        },
        {
            "big": 1,
            "due_date": 111,
            "pos_time": 5,
            "status": 1,
            "blocked": 2,
            "operations": [
                {
                    "type": 2,
                    "processing_time": 60
                }
            ]
        },
        {
            "big": 0,
            "due_date": 234,
            "pos_time": 5,
            "status": 0,
            "blocked": 0,
            "operations": [
                {
                    "type": 1,
                    "processing_time": 56
                }
            ]
        },
        {
            "big": 0,
            "due_date": 218,
            "pos_time": 5,
            "status": 3,
            "blocked": 1,
            "operations": [
                {
                    "type": 2,
                    "processing_time": 16
                }
            ]
        },
        {
            "big": 0,
            "due_date": 121,
            "pos_time": 5,
            "status": 1,
            "blocked": 1,
            "operations": [
                {
                    "type": 1,
                    "processing_time": 22
                },
                {
                    "type": 2,
                    "processing_time": 56
                }
            ]
        },
        {
            "big": 1,
            "due_date": 135,
            "pos_time": 5,
            "status": 1,
            "blocked": 0,
            "operations": [
                {
                    "type": 2,
                    "processing_time": 39
                }
            ]
        }
    ]
}