{
    "a": 50,
    "jobs": [
        {
            "big": 1,
            "due_date": 160,
            "pos_time": 5,
            "status": 1,
            "blocked": 1,
            "operations": [
                {
                    "type": 2,
                    "processing_time": 60
                },
                {
                    "type": 1,
                    "processing_time": 44
                }
            ]
        },
        {
            "big": 0,
            "due_date": 133,
            "pos_time": 5,
            "status": 1,
            "blocked": 0,
            "operations": [
                {
                    "type": 1,
                    "processing_time": 49
                }
            ]
        },
        {
            "big": 0,
            "due_date": 147,
            "pos_time": 5,
            "status": 3,
            "blocked": 1,
            "operations": [
                {
                    "type": 1,
                    "processing_time": 27
                },
                {
                    "type": 2,
                    "processing_time": 49
                }
            ]
        },
        {
            "big": 0,
            "due_date": 231,
            "pos_time": 5,
            "status": 3,
            "blocked": 2,
            "operations": [
                {
                    "type": 1,
                    "processing_time": 55
                }
            ]
        },
        {
            "big": 1,
            "due_date": 138,
            "pos_time": 5,
            "status": 3,
            "blocked": 0,
            "operations": [
                {
                    "type": 2,
                    "processing_time": 32
                },
                {
                    "type": 1,
                    "processing_time": 17
                }
            ]
        },
        {
            "big": 1,
            "due_date": 144,
            "pos_time": 5,
            "status": 3,
            "blocked": 1,
            "operations": [
                {
                    "type": 1,
                    "processing_time": 52
                },
                {
                    "type": 2,
                    "processing_time": 27
                }
            ]
        },
        {
            "big": 1,
            "due_date": 224,
            "pos_time": 5,
            "status": 0,
            "blocked": 1,
            "operations": [
                {
                    "type": 1,
                    "processing_time": 11
                }
            ]
        },
        {
            "big": 0,
            "due_date": 244,
            "pos_time": 5,
            "status": 2,
            "blocked": 2,
            "operations": [
                {
                    "type": 2,
                    "processing_time": 13
                }
            ]
        },
        {
            "big": 1,
            "due_date": 98,
            "pos_time": 5,
            "status": 0,
            "blocked": 2,
            "operations": [
                {
                    "type": 2,
                    "processing_time": 57
                }
            ]
        },
        {
            "big": 0,
            "due_date": 142,
            "pos_time": 5,
            "status": 1,
            "blocked": 0,
            "operations": [
                {
                    "type": 1,
                    "processing_time": 57
                }
            ]
        },
        {
            "big": 1,
            "due_date": 130,
            "pos_time": 5,
            "status": 1,
            "blocked": 0,
            "operations": [
                {
                    "type": 1,
                    "processing_time": 57
                }
            ]
        },
        {
            "big": 0,
            "due_date": 86,
            "pos_time": 5,
            "status": 0,
            "blocked": 2,
            "operations": [
                {
                    "type": 1,
                    "processing_time": 35
                }
            ]
        },
        {
            "big": 1,
            "due_date": 53,
            "pos_time": 5,
            "status": 3,
            "blocked": 0,
            "operations": [
                {
                    "type": 2,
                    "processing_time": 17
                },
                {
                    "type": 1,
                    "processing_time": 42
                }
            ]
        },
        {
            "big": 0,
            "due_date": 59,
            "pos_time": 5,
            "status": 3,
            "blocked": 2,
            "operations": [
                {
                    "type": 1,
                    "processing_time": 28
                }
            ]
        },
        {
            "big": 1,
            "due_date": 107,
            "pos_time": 5,
            "status": 0,
            "blocked": 2,
            "operations": [
                {
                    "type": 2,
                    "processing_time": 54
                }
            ]
        },
        {
            "big": 0,
            "due_date": 132,
            "pos_time": 5,
            "status": 2,
            "blocked": 2,
            "operations": [
                {
                    "type": 2,
                    "processing_time": 30
                }
            ]
        },
        {
            "big": 0,
            "due_date": 117,
            "pos_time": 5,
            "status": 3,
            "blocked": 2,
            "operations": [
                {
                    "type": 2,
                    "processing_time": 11
                },
                {
                    "type": 1,
                    "processing_time": 28
                }
            ]
        }
    ]
}