[
    {
        "big": 0,
        "due_date": 227,
        "pos_time": 5,
        "status": 2,
        "blocked": 2,
        "operations": [
            {
                "type": 1,
                "processing_time": 16
            },
            {
                "type": 2,
                "processing_time": 24
            }
        ]
    },
    {
        "big": 0,
        "due_date": 95,
        "pos_time": 5,
        "status": 1,
        "blocked": 0,
        "operations": [
            {
                "type": 1,
                "processing_time": 44
            },
            {
                "type": 2,
                "processing_time": 21
            }
        ]
    },
    {
        "big": 0,
        "due_date": 196,
        "pos_time": 5,
        "status": 3,
        "blocked": 1,
        "operations": [
            {
                "type": 1,
                "processing_time": 12
            },
            {
                "type": 2,
                "processing_time": 30
            }
        ]
    },
    {
        "big": 1,
        "due_date": 210,
        "pos_time": 5,
        "status": 2,
        "blocked": 0,
        "operations": [
            {
                "type": 2,
                "processing_time": 19
            }
        ]
    },
    {
        "big": 1,
        "due_date": 75,
        "pos_time": 5,
        "status": 0,
        "blocked": 1,
        "operations": [
            {
                "type": 2,
                "processing_time": 27
            }
        ]
    },
    {
        "big": 1,
        "due_date": 99,
        "pos_time": 5,
        "status": 1,
        "blocked": 0,
        "operations": [
            {
                "type": 2,
                "processing_time": 34
            }
        ]
    },
    {
        "big": 1,
        "due_date": 126,
        "pos_time": 5,
        "status": 3,
        "blocked": 2,
        "operations": [
            {
                "type": 1,
                "processing_time": 52
            },
            {
                "type": 2,
                "processing_time": 25
            }
        ]
    },
    {
        "big": 0,
        "due_date": 103,
        "pos_time": 5,
        "status": 3,
        "blocked": 2,
        "operations": [
            {
                "type": 1,
                "processing_time": 46
            }
        ]
    },
    {
        "big": 0,
        "due_date": 168,
        "pos_time": 5,
        "status": 3,
        "blocked": 0,
        "operations": [
            {
                "type": 2,
                "processing_time": 58
            }
        ]
    },
    {
        "big": 0,
        "due_date": 97,
        "pos_time": 5,
        "status": 1,
        "blocked": 2,
        "operations": [
            {
                "type": 1,
                "processing_time": 24
            }
        ]
    },
    {
        "big": 0,
        "due_date": 58,
        "pos_time": 5,
        "status": 2,
        "blocked": 0,
        "operations": [
            {
                "type": 1,
                "processing_time": 40
            }
        ]
    },
    {
        "big": 0,
        "due_date": 129,
        "pos_time": 5,
        "status": 1,
        "blocked": 2,
        "operations": [
            {
                "type": 1,
                "processing_time": 46
            },
            {
                "type": 2,
                "processing_time": 19
            }
        ]
    },
    {
        "big": 1,
        "due_date": 170,
        "pos_time": 5,
        "status": 2,
        "blocked": 0,
        "operations": [
            {
                "type": 1,
                "processing_time": 34
            },
            {
                "type": 2,
                "processing_time": 30
            }
        ]
    },
    {
        "big": 0,
        "due_date": 235,
        "pos_time": 5,
        "status": 2,
        "blocked": 0,
        "operations": [
            {
                "type": 1,
                "processing_time": 46
            },
            {
                "type": 2,
                "processing_time": 20
            }
        ]
    },
    {
        "big": 1,
        "due_date": 246,
        "pos_time": 5,
        "status": 0,
        "blocked": 0,
        "operations": [
            {
                "type": 2,
                "processing_time": 50
            }
        ]
    }
]